Design.v
`timescale 1ns / 1ps
//////////////////////////////////////////////////////////////////////////////////
// Company: 
// Engineer: 
// 
// Create Date: 21.04.2026 13:03:00
// Design Name: 
// Module Name: JKff
// Project Name: 
// Target Devices: 
// Tool Versions: 
// Description: 
// 
// Dependencies: 
// 
// Revision:
// Revision 0.01 - File Created
// Additional Comments:
// 
//////////////////////////////////////////////////////////////////////////////////


module JKff(
   input J_i, 
   input K_i, 
   input rst_i, 
   input clk_i, 
   output reg Q_o, 
   output Qbar_o
);

wire D;
assign D = (J_i & (~Q_o)) | (Q_o & (~K_i));
assign Qbar_o = ~Q_o;
always@(posedge clk_i) begin
   if(rst_i)
      Q_o <= 1'b0;
   else
      Q_o <= D;
end

endmodule

























































/*
module JKff(
   input J_i, 
   input K_i, 
   input clk_i, 
   input rst_i, 
   output reg Q_o, 
   output Qbar_o
);

wire D_i;

assign D_i = (J_i & (~Q_o)) | (Q_o & (~K_i));
assign Qbar_o = ~Q_o;
always@(posedge clk_i)
if(rst_i)
   Q_o <= 1'b0;
else
   Q_o <= D_i;

endmodule
*/

Testbench.v
`timescale 1ns / 1ps
//////////////////////////////////////////////////////////////////////////////////
// Company: 
// Engineer: 
// 
// Create Date: 21.04.2026 13:03:29
// Design Name: 
// Module Name: tb_JKff
// Project Name: 
// Target Devices: 
// Tool Versions: 
// Description: 
// 
// Dependencies: 
// 
// Revision:
// Revision 0.01 - File Created
// Additional Comments:
// 
//////////////////////////////////////////////////////////////////////////////////



module tb_JKff;
reg J_ti;
reg K_ti;
reg clk_ti;
reg rst_ti;
wire Q_to;
wire Qbar_to;

//net(s)
integer count;
integer pass;
integer fail;
reg exp_Q;
reg exp_Qbar;

//instantiation
JKff UUT(.J_i(J_ti), 
   .K_i(K_ti), 
   .clk_i(clk_ti),
   .rst_i(rst_ti),  
   .Q_o(Q_to), 
   .Qbar_o(Qbar_to));

//feeding 
initial begin
   J_ti = 1'b0; 
   K_ti = 1'b0;

#3 J_ti = 1'b1; 
   K_ti = 1'b0;
#10 J_ti = 1'b0; 
   K_ti = 1'b0;
#10 J_ti = 1'b0; 
   K_ti = 1'b1;
#10 J_ti = 1'b1; 
   K_ti = 1'b1;
#10 J_ti = 1'b0; 
   K_ti = 1'b0;

#1 $display("-----------");
$display("Checks: %d, | Pass: %d, Fail: %d", count, pass, fail);
$display("-----------");
#5 $finish;
end

//initialization
initial begin
exp_Q = 1'b0;
count = 0;
pass = 0;
fail = 0;
end

//capture
initial begin
$dumpfile("JKff.vcd");
$dumpvars(0, tb_JKff);
end

//clock
initial begin
clk_ti = 1'b0;
forever
   #5 clk_ti = ~clk_ti;
end

//Reset --Why reset is high till time 7, as clock is high at 5?
//-- reset at first clock cycle is necessary to remove race condition for all values of j and k, otherwise D, Q+ and Q will be 'X'
//-- At time 5, clk is high for the first time, reset till 6 can initialize D, Q and Q+ to 0. But exp_Q also requires to be initialized.
//-- So, at time 7, reset is set high so that these parameters can initialize. Design is proper but these are some constraints in simulation.
initial begin
rst_ti = 1'b1;
#7 rst_ti = 1'b0;
end
//If this design is so dependent on reset, what if reset is removed? will the design fail? what if reset is set 0 before first clock cycle?
//without reset, the design still behave similar, if reset is removed or set 0 before first clock cycle, D = 0 at J=0, K=1. 
//whenever this condition arrive, all DUT parameters will be initialized. then the design start working as JK flip flop.
//exp_Q will be initialized at JK = 01 or 10, at other possible combinations, X will pass.
//Add these QnA in readme.

//auto check
task check; begin 
   if(rst_ti)
      exp_Q = 1'b0;
   else 
   case ({J_ti, K_ti})
      2'b00: exp_Q = exp_Q; //hold
      2'b01: exp_Q = 1'b0; //reset
      2'b10: exp_Q = 1'b1; //set
      2'b11: exp_Q = ~exp_Q; //toggle
      default: exp_Q = 1'b0;
   endcase
   exp_Qbar = ~exp_Q;
   if((exp_Q !== Q_to) || (exp_Qbar !== Qbar_to)) begin //result matching (mismatch)
      $display("Error | Time: %0t, Clock: %b, Reset: %b | J: %b, K: %b | Q: %b, Qn: %b | Exp Q: %b, Qn: %b", $time, clk_ti, rst_ti, J_ti, K_ti, Q_to, Qbar_to, exp_Q, exp_Qbar);
      fail = fail + 1;
   end
   else ////result matching (match)
      pass = pass + 1;
   count = count + 1; //number of checks performed
end
endtask

//running auto checker
always@(posedge clk_ti)
   #1 check;

endmodule

JKff.vcd
$date
   Wed Apr 22 08:24:11 2026
$end

$version
  2025.2
  $dumpfile ("JKff.vcd") 
$end

$timescale
  1ps
$end

$scope module tb_JKff $end
$var reg 1 ! J_ti $end
$var reg 1 " K_ti $end
$var reg 1 # clk_ti $end
$var reg 1 $ rst_ti $end
$var wire 1 % Q_to $end
$var wire 1 & Qbar_to $end
$var integer 32 ' count [31:0] $end
$var integer 32 ( pass [31:0] $end
$var integer 32 ) fail [31:0] $end
$var reg 1 * exp_Q $end
$var reg 1 + exp_Qbar $end
$scope module UUT $end
$var wire 1 , J_i $end
$var wire 1 - K_i $end
$var wire 1 . rst_i $end
$var wire 1 / clk_i $end
$var reg 1 0 Q_o $end
$var wire 1 & Qbar_o $end
$var wire 1 1 D $end
$upscope $end
$scope task check $end
$upscope $end
$upscope $end
$enddefinitions $end

#0
$dumpvars
0!
0"
0#
1$
x%
x&
b0 '
b0 (
b0 )
0*
x+
0,
0-
1.
0/
x0
x1
$end

#3000
1!
1,

#5000
1#
0%
1&
1/
00
11

#6000
b1 '
b1 (
1+

#7000
0$
0.

#10000
0#
0/

#13000
0!
0,
01

#15000
1#
1/

#16000
b10 '
b10 (

#20000
0#
0/

#23000
1"
1-

#25000
1#
1/

#26000
b11 '
b11 (

#30000
0#
0/

#33000
1!
1,
11

#35000
1#
1%
0&
1/
10
01

#36000
b100 '
b100 (
1*
0+

#40000
0#
0/

#43000
0!
0"
0,
0-
11

#45000
1#
1/

#46000
b101 '
b101 (
